odoo/addons/edi_stock_oca/README.rst
odoo/addons/edi_stock_oca/__init__.py
odoo/addons/edi_stock_oca/__manifest__.py
odoo/addons/edi_stock_oca/components/__init__.py
odoo/addons/edi_stock_oca/components/listeners.py
odoo/addons/edi_stock_oca/data/edi_configuration.xml
odoo/addons/edi_stock_oca/demo/edi_backend.xml
odoo/addons/edi_stock_oca/demo/edi_configuration.xml
odoo/addons/edi_stock_oca/demo/edi_exchange_type.xml
odoo/addons/edi_stock_oca/i18n/edi_stock_oca.pot
odoo/addons/edi_stock_oca/i18n/it.po
odoo/addons/edi_stock_oca/models/__init__.py
odoo/addons/edi_stock_oca/models/res_partner.py
odoo/addons/edi_stock_oca/models/stock_picking.py
odoo/addons/edi_stock_oca/readme/CONTRIBUTORS.md
odoo/addons/edi_stock_oca/readme/DESCRIPTION.md
odoo/addons/edi_stock_oca/static/description/icon.png
odoo/addons/edi_stock_oca/static/description/index.html
odoo/addons/edi_stock_oca/tests/__init__.py
odoo/addons/edi_stock_oca/tests/test_edi.py
odoo/addons/edi_stock_oca/views/res_partner.xml
odoo/addons/edi_stock_oca/views/stock_picking.xml
odoo_addon_edi_stock_oca-18.0.1.0.1.dist-info/METADATA
odoo_addon_edi_stock_oca-18.0.1.0.1.dist-info/WHEEL
odoo_addon_edi_stock_oca-18.0.1.0.1.dist-info/top_level.txt
odoo_addon_edi_stock_oca-18.0.1.0.1.dist-info/RECORD
